kProcessor.py
_kProcessor.cpython-36m-x86_64-linux-gnu.so
kProcessor-1.2.0.dist-info/METADATA
kProcessor-1.2.0.dist-info/RECORD
kProcessor-1.2.0.dist-info/top_level.txt
kProcessor-1.2.0.dist-info/LICENSE
kProcessor-1.2.0.dist-info/WHEEL
kProcessor.libs/libgomp-a34b3233.so.1.0.0
kProcessor.libs/libbz2-a273e504.so.1.0.6
kProcessor.libs/libz-745e0a09.so.1.2.7
