Metadata-Version: 2.1
Name: kProcessor
Version: 1.2.0
Summary: kProcessor Python interface
Home-page: https://github.com/dib-lab/kProcessor
Author: Mostafa Shokrof, Mohamed Abuelanin, Tamer Mansour
Author-email: mostafa.shokrof@gmail.com, mabuelanin@gmail.com, drtamermansour@gmail.com
License: BSD 3-Clause
Project-URL: Bug Reports, https://github.com/dib-lab/kProcessor/issues
Project-URL: Source, https://github.com/dib-lab/kProcessor
Platform: UNKNOWN
Classifier: License :: OSI Approved :: Apache Software License
Classifier: Development Status :: 3 - Alpha
Classifier: Operating System :: POSIX :: Linux
Classifier: Programming Language :: Python
Classifier: Programming Language :: Python :: 3
Classifier: Programming Language :: Python :: 3.6
Classifier: Programming Language :: Python :: 3.7
Classifier: Programming Language :: Python :: 3.8
Classifier: Programming Language :: Python :: 3.9
Requires-Python: >=3.6
License-File: LICENSE
